LICENSE
MANIFEST.in
README.rst
setup.py
django_swagger_ui.egg-info/PKG-INFO
django_swagger_ui.egg-info/SOURCES.txt
django_swagger_ui.egg-info/dependency_links.txt
django_swagger_ui.egg-info/requires.txt
django_swagger_ui.egg-info/top_level.txt
swagger_ui/__init__.py
swagger_ui/admin.py
swagger_ui/apps.py
swagger_ui/models.py
swagger_ui/tests.py
swagger_ui/urls.py
swagger_ui/views.py
swagger_ui/migrations/__init__.py
swagger_ui/static/swagger-ui/dist/swagger-ui-bundle.js
swagger_ui/static/swagger-ui/dist/swagger-ui-standalone-preset.js
swagger_ui/templates/swagger_base.html